solr2rabbitmq/__init__.py
solr2rabbitmq-1.1.6.data/scripts/solr2rabbitmq
solr2rabbitmq-1.1.6.dist-info/LICENSE
solr2rabbitmq-1.1.6.dist-info/METADATA
solr2rabbitmq-1.1.6.dist-info/WHEEL
solr2rabbitmq-1.1.6.dist-info/top_level.txt
solr2rabbitmq-1.1.6.dist-info/RECORD
