Metadata-Version: 2.1
Name: solr2rabbitmq
Version: 1.1.6
Summary: Asynchronous RabbitMQ transfer job library from Apache Solr
Home-page: https://github.com/mantis-software-company/solr2rabbitmq
Author: Furkan Kalkan
Author-email: furkankalkan@mantis.com.tr
License: UNKNOWN
Platform: all
Classifier: License :: OSI Approved :: Apache Software License
Classifier: Topic :: Internet
Classifier: Topic :: Software Development
Classifier: Topic :: Software Development :: Libraries
Classifier: Topic :: Software Development :: Testing
Classifier: Intended Audience :: Developers
Classifier: Operating System :: MacOS
Classifier: Operating System :: POSIX
Classifier: Operating System :: Microsoft
Classifier: Programming Language :: Python
Classifier: Programming Language :: Python :: 3.6
Classifier: Programming Language :: Python :: 3.7
Classifier: Programming Language :: Python :: 3.8
Requires-Dist: aiohttp
Requires-Dist: aio-pika
Requires-Dist: jinja2
